common/__init__.py
common/config.py
common/constants.py
common/path.py
common/po.py
common/prompt.py
common/utils.py
compiler/README.md
compiler/__init__.py
compiler/compiler.py
django_jinx-0.0.1.dist-info/METADATA
django_jinx-0.0.1.dist-info/WHEEL
django_jinx-0.0.1.dist-info/licenses/LICENSE
exporter/README.md
exporter/__init__.py
exporter/exporter.py
extractor/README.md
extractor/__init__.py
extractor/extractor.py
marker/.DS_Store
marker/README.md
marker/__init__.py
marker/marker.py
marker/plugins/__init__.py
marker/plugins/file_filter.py
marker/plugins/str_conditions.py
marker/utils/__init__.py
marker/utils/token.py
marker/utils/translation_func.py
translator/README.md
translator/__init__.py
translator/provider/__init__.py
translator/provider/base.py
translator/provider/google_api.py
translator/provider/provider.py
translator/provider/youdao_client.py
translator/translator.py
django_jinx-0.0.1.dist-info/RECORD
