Metadata-Version: 2.1
Name: django-jinx
Version: 0.0.1
Summary: A full-stack i18n solution for Django
Keywords: django i18n internationalization translation localization l10n django-i18n django-internationalization django-translation django-localization django-l10n
Author-Email: kiritoscs <kiritoscs@gmail.com>
License: MIT License
Classifier: Programming Language :: Python :: 3
Classifier: License :: OSI Approved :: MIT License
Classifier: Operating System :: OS Independent
Project-URL: Homepage, https://github.com/kiritoscs/jinx
Project-URL: Bug tracker, https://github.com/kiritoscs/jinx/issues
Requires-Python: >=3.11
Requires-Dist: arrow>=1.2.2
Requires-Dist: click>=8.1.3
Requires-Dist: polib>=1.2.0
Requires-Dist: requests>=2.28.2
Requires-Dist: rich>=13.3.2
